skadoo/__init__.py
skadoo/flags.py
skadoo/root.py
skadoo/utils.py
tests/__init__.py
tests/examples.py
tests/test_package.py
skadoo-0.0.0b5.dist-info/LICENSE
skadoo-0.0.0b5.dist-info/METADATA
skadoo-0.0.0b5.dist-info/WHEEL
skadoo-0.0.0b5.dist-info/top_level.txt
skadoo-0.0.0b5.dist-info/RECORD
